XhsarkDataCollection/__init__.py
XhsarkDataCollection/_login.py
XhsarkDataCollection/collector.py
XhsarkDataCollection/py.typed
XhsarkDataCollection/datacenter/_utils.py
XhsarkDataCollection/datacenter/datacenter.py
XhsarkDataCollection/datacenter/live.py
xhsark_data_collection-1.0.4.dist-info/METADATA
xhsark_data_collection-1.0.4.dist-info/WHEEL
xhsark_data_collection-1.0.4.dist-info/licenses/LICENSE
xhsark_data_collection-1.0.4.dist-info/RECORD
