Metadata-Version: 2.4
Name: xhsark-data-collection
Version: 1.0.4
Summary: XHS ARK Data Collection
Author: martianbugs
License-File: LICENSE
Requires-Python: >=3.12
Requires-Dist: browser-automation-launcher>=1.0.7
